brynq_sdk_bob/__init__.py
brynq_sdk_bob/bank.py
brynq_sdk_bob/company.py
brynq_sdk_bob/custom_tables.py
brynq_sdk_bob/documents.py
brynq_sdk_bob/employment.py
brynq_sdk_bob/named_lists.py
brynq_sdk_bob/payments.py
brynq_sdk_bob/payroll_history.py
brynq_sdk_bob/people.py
brynq_sdk_bob/reports.py
brynq_sdk_bob/salaries.py
brynq_sdk_bob/timeoff.py
brynq_sdk_bob/work.py
brynq_sdk_bob/schemas/__init__.py
brynq_sdk_bob/schemas/bank.py
brynq_sdk_bob/schemas/custom_tables.py
brynq_sdk_bob/schemas/employment.py
brynq_sdk_bob/schemas/named_lists.py
brynq_sdk_bob/schemas/payments.py
brynq_sdk_bob/schemas/payroll_history.py
brynq_sdk_bob/schemas/people.py
brynq_sdk_bob/schemas/salary.py
brynq_sdk_bob/schemas/timeoff.py
brynq_sdk_bob/schemas/work.py
brynq_sdk_bob-2.9.2.dist-info/METADATA
brynq_sdk_bob-2.9.2.dist-info/WHEEL
brynq_sdk_bob-2.9.2.dist-info/top_level.txt
brynq_sdk_bob-2.9.2.dist-info/RECORD
