Metadata-Version: 2.4
Name: brynq_sdk_bob
Version: 2.9.2
Summary: Bob wrapper from BrynQ
Author: BrynQ
Author-email: support@brynq.com
License: BrynQ License
Requires-Dist: brynq-sdk-brynq<5,>=4
Requires-Dist: pandas<3.0.0,>=2.2.0
Dynamic: author
Dynamic: author-email
Dynamic: description
Dynamic: license
Dynamic: requires-dist
Dynamic: summary
